ProgramizCJiaochengChuyiFix1/README.md
ProgramizCJiaochengChuyiFix1/__init__.py
ProgramizCJiaochengChuyiFix1/__main__.py
ProgramizCJiaochengChuyiFix1/file.epub
ProgramizCJiaochengChuyiFix1/index.html
ProgramizCJiaochengChuyiFix1/css/__init__.py
ProgramizCJiaochengChuyiFix1/css/annotations.css
ProgramizCJiaochengChuyiFix1/css/main.css
ProgramizCJiaochengChuyiFix1/css/normalize.css
ProgramizCJiaochengChuyiFix1/css/popup.css
ProgramizCJiaochengChuyiFix1/font/__init__.py
ProgramizCJiaochengChuyiFix1/font/fontello.eot
ProgramizCJiaochengChuyiFix1/font/fontello.svg
ProgramizCJiaochengChuyiFix1/font/fontello.ttf
ProgramizCJiaochengChuyiFix1/font/fontello.woff
ProgramizCJiaochengChuyiFix1/img/__init__.py
ProgramizCJiaochengChuyiFix1/img/annotator-glyph-sprite.png
ProgramizCJiaochengChuyiFix1/img/annotator-icon-sprite.png
ProgramizCJiaochengChuyiFix1/img/apple-touch-icon.png
ProgramizCJiaochengChuyiFix1/img/cancelfullscreen.png
ProgramizCJiaochengChuyiFix1/img/close.png
ProgramizCJiaochengChuyiFix1/img/fullscreen.png
ProgramizCJiaochengChuyiFix1/img/loader.gif
ProgramizCJiaochengChuyiFix1/img/menu-icon.png
ProgramizCJiaochengChuyiFix1/img/save.png
ProgramizCJiaochengChuyiFix1/img/saved.png
ProgramizCJiaochengChuyiFix1/img/settings-s.png
ProgramizCJiaochengChuyiFix1/img/settings.png
ProgramizCJiaochengChuyiFix1/img/star.png
ProgramizCJiaochengChuyiFix1/js/__init__.py
ProgramizCJiaochengChuyiFix1/js/epub.js
ProgramizCJiaochengChuyiFix1/js/epub.min.js
ProgramizCJiaochengChuyiFix1/js/epub.min.map
ProgramizCJiaochengChuyiFix1/js/hooks.min.js
ProgramizCJiaochengChuyiFix1/js/hooks.min.map
ProgramizCJiaochengChuyiFix1/js/reader.js
ProgramizCJiaochengChuyiFix1/js/reader.js.map
ProgramizCJiaochengChuyiFix1/js/reader.min.js
ProgramizCJiaochengChuyiFix1/js/reader.min.map
ProgramizCJiaochengChuyiFix1/js/hooks/__init__.py
ProgramizCJiaochengChuyiFix1/js/hooks/extensions/__init__.py
ProgramizCJiaochengChuyiFix1/js/hooks/extensions/highlight.js
programiz_c_jiaocheng_chuyi_fix1-2025.3.24.1.dist-info/METADATA
programiz_c_jiaocheng_chuyi_fix1-2025.3.24.1.dist-info/WHEEL
programiz_c_jiaocheng_chuyi_fix1-2025.3.24.1.dist-info/entry_points.txt
programiz_c_jiaocheng_chuyi_fix1-2025.3.24.1.dist-info/top_level.txt
programiz_c_jiaocheng_chuyi_fix1-2025.3.24.1.dist-info/RECORD
